BOOK_NLP_fr/BookNLP_fr.py
BOOK_NLP_fr/BookNLP_fr_add_entities_features.py
BOOK_NLP_fr/BookNLP_fr_coreference_resolution_module.py
BOOK_NLP_fr/BookNLP_fr_extract_attributes.py
BOOK_NLP_fr/BookNLP_fr_gender.py
BOOK_NLP_fr/BookNLP_fr_generate_characters_dict.py
BOOK_NLP_fr/BookNLP_fr_generate_tokens_and_entities_from_sacr.py
BOOK_NLP_fr/BookNLP_fr_generate_tokens_df.py
BOOK_NLP_fr/BookNLP_fr_generate_tokens_embeddings_tensor.py
BOOK_NLP_fr/BookNLP_fr_load_save_functions.py
BOOK_NLP_fr/BookNLP_fr_mentions_detection_module.py
BOOK_NLP_fr/BookNLP_fr_number.py
BOOK_NLP_fr/__init__.py
BOOK_NLP_fr/data/insee_names_fr_1900_2023.csv
BOOK_NLP_fr-10000.100.36.dist-info/LICENSE
BOOK_NLP_fr-10000.100.36.dist-info/METADATA
BOOK_NLP_fr-10000.100.36.dist-info/WHEEL
BOOK_NLP_fr-10000.100.36.dist-info/top_level.txt
BOOK_NLP_fr-10000.100.36.dist-info/RECORD
