Metadata-Version: 2.1
Name: BOOK_NLP_fr
Version: 10000.100.36
Summary: BOOK_NLP_fr
Author-email: Antoine BOURGOIS <antoine.bourgois@protonmail.com>
Project-URL: Homepage, https://github.com/pypa/sampleproject
Project-URL: Issues, https://github.com/pypa/sampleproject/issues
Classifier: Programming Language :: Python :: 3
Classifier: License :: OSI Approved :: MIT License
Classifier: Operating System :: OS Independent
Requires-Python: >=3.7
License-File: LICENSE
Requires-Dist: pandas>=1.0.0
Requires-Dist: tqdm>=4.0.0
Requires-Dist: plotly>=5.0.0
Requires-Dist: torch>=1.0.0
Requires-Dist: spacy>=3.0.0
Requires-Dist: transformers>=4.0.0
Requires-Dist: TorchCRF>=1.0.0
Requires-Dist: scikit-learn>=0.24.0
Requires-Dist: numpy>=1.20.0
Requires-Dist: tabulate>=0.8.0
Requires-Dist: protobuf>=3.0.0
Requires-Dist: tokenizers>=0.10.0
Requires-Dist: sentencepiece>=0.1.0
